volcano/general/__init__.py
volcano/general/bin.py
volcano/general/log.py
volcano/general/modbus.py
volcano/general/named_parameters.py
volcano/general/stddef.py
volcano/general/stdint.py
volcano/general/stdsvc.py
volcano/general/stdsvcdef.py
volcano/general/tstamp.py
volcano/general/variant.py
volcano/general/vector.py
volcano/general/xml_reader.py
volcano_general-1.0.0.dist-info/LICENSE
volcano_general-1.0.0.dist-info/METADATA
volcano_general-1.0.0.dist-info/WHEEL
volcano_general-1.0.0.dist-info/top_level.txt
volcano_general-1.0.0.dist-info/RECORD
